webengine/__init__.py
webengine/cli.py
uzweb-0.0.1.dist-info/METADATA
uzweb-0.0.1.dist-info/WHEEL
uzweb-0.0.1.dist-info/entry_points.txt
uzweb-0.0.1.dist-info/top_level.txt
uzweb-0.0.1.dist-info/RECORD
