Metadata-Version: 2.1
Name: uzweb
Version: 0.0.1
Summary: no description
Author: Sizning Ismingiz
Author-email: your.email@example.com
Classifier: Programming Language :: Python :: 3
Classifier: License :: OSI Approved :: MIT License
Classifier: Operating System :: OS Independent
